fastapi_intro/__init__.py
fastapi_intro/asyncio_test.py
fastapi_intro/authentication/__init__.py
fastapi_intro/authentication/auth_settings.py
fastapi_intro/authentication/auth_utils.py
fastapi_intro/authentication/schema.py
fastapi_intro/database/crud.py
fastapi_intro/database/database.py
fastapi_intro/database/models.py
fastapi_intro/database/schema.py
fastapi_intro/database.db
fastapi_intro/main.py
fastapi_intro/tests/__init__.py
fastapi_intro/tests/database.db
fastapi_intro/tests/test_fastapi_intro.py
fastapi_intro/thread_test.py
fastapi_intro-1.1.0.dist-info/WHEEL
fastapi_intro-1.1.0.dist-info/METADATA
fastapi_intro-1.1.0.dist-info/RECORD
