Metadata-Version: 2.1
Name: fastapi-intro
Version: 1.1.0
Summary: 
Author: prabal
Author-email: prabal01pathak@gmail.com
Requires-Python: >=3.9,<4.0
Classifier: Programming Language :: Python :: 3
Classifier: Programming Language :: Python :: 3.10
Classifier: Programming Language :: Python :: 3.9
Requires-Dist: SQLAlchemy (>=1.4.36,<2.0.0)
Requires-Dist: fastapi (>=0.76.0,<0.77.0)
Requires-Dist: passlib[bcrypt] (>=1.7.4,<2.0.0)
Requires-Dist: pydantic[email] (>=1.9.0,<2.0.0)
Requires-Dist: pytest (==7.1.2)
Requires-Dist: python-jose[cryptography] (>=3.3.0,<4.0.0)
Requires-Dist: python-multipart (>=0.0.5,<0.0.6)
Requires-Dist: uvicorn[standard] (>=0.17.6,<0.18.0)
